rtl/project.sv
// ─────────────────────────────────────────────────────────────────────────────
//  EEE703128 — Bài kiểm tra số 2 · KHUNG MẪU
//  Quy ước bắt buộc của chuỗi công cụ:
//    · `default_nettype none  ở đầu và `default_nettype wire ở cuối
//    · rst_n tích cực mức THẤP (rst_n = 0 nghĩa là đang reset)
//    · Mọi chân ra phải được gán giá trị, không được để hở
//    · uio_oe[i] = 1 nghĩa là chân hai chiều thứ i làm ĐẦU RA
// ─────────────────────────────────────────────────────────────────────────────
`default_nettype none

module tt_um_eee703128_24100665 (
    input  wire [7:0] ui_in,    // 8 chân vào riêng
    output wire [7:0] uo_out,   // 8 chân ra riêng
    input  wire [7:0] uio_in,   // 8 chân hai chiều — chiều vào
    output wire [7:0] uio_out,  // 8 chân hai chiều — chiều ra
    output wire [7:0] uio_oe,   // 1 = chân tương ứng là đầu ra
    input  wire       ena,      // luôn bằng 1 khi thiết kế được chọn
    input  wire       clk,      // xung nhịp hệ thống
    input  wire       rst_n     // reset, TÍCH CỰC MỨC THẤP
);

    // ══════════════════ PHẦN CỦA EM — BẮT ĐẦU ══════════════════
    //
    // Ví dụ mẫu dưới đây là case threshold_alarm của học phần (tuần 8–10):
    //     alarm = 1 khi sample >= threshold
    // Nó KHÔNG nằm trong 80 đề — chỉ để em thấy cách nối chân.
    //
    // Ánh xạ chân của ví dụ này:
    //     ui_in [7:0] = sample
    //     uio_in[7:0] = threshold
    //     uo_out[0]   = alarm
    //     uo_out[7:1] = 0  (phải gán, không được để hở)

    wire [7:0] sample    = ui_in;
    wire [7:0] threshold = uio_in;
    wire       alarm     = (sample >= threshold);

    assign uo_out  = {7'b0, alarm};
    assign uio_out = 8'b0;      // ví dụ này không dùng chân hai chiều làm đầu ra
    assign uio_oe  = 8'b0;      // ...nên toàn bộ để ở chiều VÀO

    // ══════════════════ PHẦN CỦA EM — KẾT THÚC ══════════════════

    // Chống cảnh báo "tín hiệu khai báo mà không dùng".
    // Nếu đề của em là mạch tổ hợp thì clk và rst_n sẽ không được dùng —
    // dòng này giữ cho công cụ không kêu. Đề tuần tự thì bỏ clk, rst_n ra khỏi đây.
    wire _unused = &{ena, clk, rst_n, 1'b0};

endmodule

`default_nettype wire

tb/tb.sv
// ─────────────────────────────────────────────────────────────────────────────
//  Testbench mẫu — EEE703128 Bài kiểm tra số 2
//
//  Testbench này làm ba việc, và báo cáo của em cần cả ba:
//    1. Sinh kích thích đầu vào theo các ca kiểm thử của đề
//    2. So kết quả thu được với kết quả MONG ĐỢI (tự tính tay trước)
//    3. Ghi file .vcd để mở bằng GTKWave / Surfer và chụp waveform đưa vào báo cáo
//
//  Chạy thử trên máy (nếu có Icarus Verilog):
//      iverilog -g2012 -o tb.out test/tb.v src/project.v && vvp tb.out
//
//  Không cài được cũng không sao — chuỗi công cụ trên GitHub chạy hộ.
// ─────────────────────────────────────────────────────────────────────────────
`default_nettype none
`timescale 1ns / 1ps

module tb;

    reg  [7:0] ui_in, uio_in;
    reg        ena, clk, rst_n;
    wire [7:0] uo_out, uio_out, uio_oe;

    integer so_ca  = 0;   // đã chạy bao nhiêu ca
    integer so_sai = 0;   // sai bao nhiêu ca

    tt_um_eee703128_24100665 dut (
        .ui_in(ui_in), .uo_out(uo_out),
        .uio_in(uio_in), .uio_out(uio_out), .uio_oe(uio_oe),
        .ena(ena), .clk(clk), .rst_n(rst_n)
    );

    // Xung nhịp 10 ns (100 MHz). Đề tổ hợp không dùng nhưng cứ để chạy.
    initial clk = 0;
    always #5 clk = ~clk;

    // ── Nhiệm vụ kiểm một ca ──────────────────────────────────────────────
    // Sửa hai tham số cho khớp đề của em.
    task kiem;
        input [7:0] a;          // giá trị đưa vào ui_in
        input [7:0] b;          // giá trị đưa vào uio_in
        input [7:0] mong_doi;   // giá trị MONG ĐỢI ở uo_out — tự tính tay
        input [255:0] ten;      // tên ca kiểm thử (tối đa 32 ký tự)
        begin
            ui_in  = a;
            uio_in = b;
            #10;                            // chờ mạch ổn định
            so_ca = so_ca + 1;
            if (uo_out === mong_doi)
                $display("  ✓ %0s | ui=%0d uio=%0d -> uo=%0d", ten, a, b, uo_out);
            else begin
                so_sai = so_sai + 1;
                $display("  ✗ %0s | ui=%0d uio=%0d -> uo=%0d  (MONG ĐỢI %0d)",
                         ten, a, b, uo_out, mong_doi);
            end
        end
    endtask

    initial begin
        $dumpfile("tb.vcd");
        $dumpvars(0, tb);

        ena = 1; rst_n = 0; ui_in = 0; uio_in = 0;
        #20 rst_n = 1;          // nhả reset
        #10;

        $display("");
        $display("=== CA KIEM THU ===");

        // ══════════════════ CA KIỂM THỬ CỦA EM — BẮT ĐẦU ══════════════════
        // Các ca dưới đây kiểm ví dụ mẫu threshold_alarm (alarm = sample >= threshold).
        // Xoá đi và thay bằng các ca ở cột "Ca kiểm thử tối thiểu" của đề em.
        // Nhớ thêm ít nhất hai ca do em tự nghĩ — rubric tiêu chí 2 có tính điểm phần này.

        kiem(  0,   0, 8'd1, "bang nhau o 0    ");   // 0 >= 0   -> alarm = 1
        kiem(  0,   1, 8'd0, "duoi nguong      ");   // 0 >= 1   -> alarm = 0
        kiem(200, 120, 8'd1, "tren nguong      ");   // 200>=120 -> alarm = 1
        kiem(120, 120, 8'd1, "dung bien        ");   // 120>=120 -> alarm = 1
        kiem(119, 120, 8'd0, "duoi bien 1 don vi");  // 119>=120 -> alarm = 0
        kiem(255,   0, 8'd1, "gia tri lon nhat ");   // 255>=0   -> alarm = 1
        kiem(  0, 255, 8'd0, "nguong lon nhat  ");   // 0 >= 255 -> alarm = 0

        // ══════════════════ CA KIỂM THỬ CỦA EM — KẾT THÚC ══════════════════

        $display("");
        $display("=== KET QUA: %0d ca, %0d sai ===", so_ca, so_sai);
        if (so_sai == 0) $display("TAT CA CA KIEM THU DEU DAT");
        else             $display("CON %0d CA SAI — sua RTL roi chay lai", so_sai);
        $display("");
        #20 $finish;
    end

endmodule

`default_nettype wire

tb.vcd
$date
	Thu Sep 17 19:40:01 2026
$end
$version
	Icarus Verilog
$end
$timescale
	1ps
$end
$scope module tb $end
$var wire 8 ! uio_oe [7:0] $end
$var wire 8 " uio_out [7:0] $end
$var wire 8 # uo_out [7:0] $end
$var reg 1 $ clk $end
$var reg 1 % ena $end
$var reg 1 & rst_n $end
$var reg 8 ' ui_in [7:0] $end
$var reg 8 ( uio_in [7:0] $end
$var integer 32 ) so_ca [31:0] $end
$var integer 32 * so_sai [31:0] $end
$scope module dut $end
$var wire 1 $ clk $end
$var wire 1 % ena $end
$var wire 1 & rst_n $end
$var wire 8 + sample [7:0] $end
$var wire 8 , threshold [7:0] $end
$var wire 8 - ui_in [7:0] $end
$var wire 8 . uio_in [7:0] $end
$var wire 8 / uio_oe [7:0] $end
$var wire 8 0 uio_out [7:0] $end
$var wire 8 1 uo_out [7:0] $end
$var wire 1 2 alarm $end
$var wire 1 3 _unused $end
$upscope $end
$scope task kiem $end
$var reg 8 4 a [7:0] $end
$var reg 8 5 b [7:0] $end
$var reg 8 6 mong_doi [7:0] $end
$var reg 256 7 ten [255:0] $end
$upscope $end
$upscope $end
$enddefinitions $end
$comment Show the parameter values. $end
$dumpall
$end
#0
$dumpvars
bx 7
bx 6
bx 5
bx 4
03
12
b1 1
b0 0
b0 /
b0 .
b0 -
b0 ,
b0 +
b0 *
b0 )
b0 (
b0 '
0&
1%
0$
b1 #
b0 "
b0 !
$end
#5000
1$
#10000
0$
#15000
1$
#20000
0$
1&
#25000
1$
#30000
0$
b110001001100001011011100110011100100000011011100110100001100001011101010010000001101111001000000011000000100000001000000010000000100000 7
b1 6
b0 5
b0 4
#35000
1$
#40000
0$
b0 #
b0 1
02
b1 ,
b1 (
b1 .
b110010001110101011011110110100100100000011011100110011101110101011011110110111001100111001000000010000000100000001000000010000000100000 7
b0 6
b1 5
b1 )
#45000
1$
#50000
0$
b1111000 ,
b1111000 (
b1111000 .
b1 #
b1 1
12
b11001000 +
b11001000 '
b11001000 -
b111010001110010011001010110111000100000011011100110011101110101011011110110111001100111001000000010000000100000001000000010000000100000 7
b1 6
b1111000 5
b11001000 4
b10 )
#55000
1$
#60000
0$
b1111000 +
b1111000 '
b1111000 -
b110010001110101011011100110011100100000011000100110100101100101011011100010000000100000001000000010000000100000001000000010000000100000 7
b1111000 4
b11 )
#65000
1$
#70000
0$
b0 #
b0 1
02
b1110111 +
b1110111 '
b1110111 -
b11001000111010101101111011010010010000001100010011010010110010101101110001000000011000100100000011001000110111101101110001000000111011001101001 7
b0 6
b1110111 4
b100 )
#75000
1$
#80000
0$
b0 ,
b0 (
b0 .
b1 #
b1 1
12
b11111111 +
b11111111 '
b11111111 -
b110011101101001011000010010000001110100011100100110100100100000011011000110111101101110001000000110111001101000011000010111010000100000 7
b1 6
b0 5
b11111111 4
b101 )
#85000
1$
#90000
0$
b0 #
b0 1
02
b11111111 ,
b11111111 (
b11111111 .
b0 +
b0 '
b0 -
b110111001100111011101010110111101101110011001110010000001101100011011110110111000100000011011100110100001100001011101000010000000100000 7
b0 6
b11111111 5
b0 4
b110 )
#95000
1$
#100000
0$
b111 )
